{
"gongzhonghao":"消屏器",  
"versionName":"趣安卓", 
"yinsizhengce":"趣安卓", 
"yonghuxieyi":"趣安卓", 
"yuntime":"2024-08-06 00:00:00.000",
"qqjiaqun":"sP-D0cCfMtzQixaH-g7InzHd0lMpqUOY", 
"shiyongshouce":"https://mp.weixin.qq.com/s/MyzUjRldhvva7Brgf94DuQ",
"fankuirukou":"https://support.qq.com/products/539515",
"downloadUrl_1":"https://520821.cn/helphtml/quanzhuo/quanzhuo.html",
"downloadUrl_2":"http://xiazai.miaoqidong.com/d/36659644-53918021-a72837", 
"downloadUrl_3":"https://www.123pan.com/s/eyfxjv-MQvKd.html",  
"isCancel":"true",
"t4notwork":"false",
"versionCode":120,
"des":"https://520821.cn/rule/quanzhuo.html"
}